witertools/__init__.py
witertools/iterator_to_list.py
witertools/itertools/__init__.py
witertools/more_itertools/__init__.py
witertools-1.0.1.dist-info/WHEEL
witertools-1.0.1.dist-info/METADATA
witertools-1.0.1.dist-info/RECORD
