Metadata-Version: 2.1
Name: witertools
Version: 1.0.1
Summary: Witertools - Tools to wrap iterator functions, to consume the whole iterator and return a list.  Avoid sprinklist list(...)
Keywords: itertools,iterator,iteration,filter,peek,peekable,list,more-itertools
Author-email: Doug Ransom <doug@ransom.vip>
Requires-Python: >=3.0
Classifier: Development Status :: 5 - Production/Stable
Classifier: Intended Audience :: Developers
Classifier: Natural Language :: English
Classifier: License :: OSI Approved :: MIT License
Classifier: Programming Language :: Python :: 3
Classifier: Programming Language :: Python :: 3.6
Classifier: Programming Language :: Python :: 3.7
Classifier: Programming Language :: Python :: 3.8
Classifier: Programming Language :: Python :: 3.9
Classifier: Programming Language :: Python :: 3.10
Classifier: Programming Language :: Python :: 3 :: Only
Classifier: Programming Language :: Python :: Implementation :: CPython
Classifier: Programming Language :: Python :: Implementation :: PyPy
Classifier: Topic :: Software Development :: Libraries
Requires-Dist: pytest >=7.1.2 ; extra == "test"
Requires-Dist: pytest-cov ; extra == "test"
Requires-Dist: more-itertools ; extra == "test"
Project-URL: source, https://github.com/dougransom/witertools
Provides-Extra: test
